djvuviewer/__init__.py
djvuviewer/djvu_actions.py
djvuviewer/djvu_bundle.py
djvuviewer/djvu_catalog.py
djvuviewer/djvu_cmd.py
djvuviewer/djvu_config.py
djvuviewer/djvu_context.py
djvuviewer/djvu_core.py
djvuviewer/djvu_debug.py
djvuviewer/djvu_files.py
djvuviewer/djvu_image_job.py
djvuviewer/djvu_manager.py
djvuviewer/djvu_processor.py
djvuviewer/djvu_viewer.py
djvuviewer/djvu_webcmd.py
djvuviewer/djvu_wikimages.py
djvuviewer/download.py
djvuviewer/grid_view.py
djvuviewer/image_convert.py
djvuviewer/multilang_querymanager.py
djvuviewer/packager.py
djvuviewer/version.py
djvuviewer/webserver.py
djvuviewer/wiki_images.py
djvuviewer_examples/README.md
djvuviewer_examples/__init__.py
djvuviewer_examples/djvu_data.db
djvuviewer_examples/djvu_queries.yaml
djvuviewer_examples/djvuviewer.puml
djvuviewer_examples/djvu_images/AB1932-Ramrath.tar
djvuviewer_examples/djvu_images/AB1932-Ramrath.zip
djvuviewer_examples/djvu_images/AB1938_Kreis-Beckum_Inhaltsverz.tar
djvuviewer_examples/djvu_images/AB1938_Kreis-Beckum_Inhaltsverz.zip
djvuviewer_examples/djvu_images/AB1953-Gohr.tar
djvuviewer_examples/djvu_images/AB1953-Gohr.zip
djvuviewer_examples/djvu_images/Plauen-AB-1938.tar
djvuviewer_examples/djvu_images/Plauen-AB-1938.zip
djvuviewer_examples/images/1/1e/AB1953-Gohr.djvu
djvuviewer_examples/images/c/c7/AB1938 Kreis-Beckum_Titel_0001.djvu
djvuviewer_examples/images/c/c7/AB1938_Kreis-Beckum_Inhaltsverz.djvu
djvuviewer_examples/images/c/c7/AB1938_Kreis-Beckum_Inhaltsverz_bundled.djvu
djvuviewer_examples/images/c/c7/s003_0001.djvu
djvuviewer_examples/images/c/c7/s004_0001.djbz
djvuviewer_examples/images/c/c7/s004_0001.djvu
djvuviewer_examples/images/c/ce/Plauen-AB-1938.djvu
djvuviewer_examples/images/f/ff/AB1932-Ramrath.djvu
djvu_viewer-0.8.0.dist-info/METADATA
djvu_viewer-0.8.0.dist-info/WHEEL
djvu_viewer-0.8.0.dist-info/entry_points.txt
djvu_viewer-0.8.0.dist-info/licenses/LICENSE
djvu_viewer-0.8.0.dist-info/RECORD
