Metadata-Version: 2.4
Name: djvu-viewer
Version: 0.8.0
Summary: DjVu Viewer and tarball converter
Project-URL: Home, https://github.com/WolfgangFahl/genwiki2024
Project-URL: Documentation, https://wiki.bitplan.com/index.php/genwiki2024
Project-URL: Source, https://github.com/WolfgangFahl/genwiki2024
Author-email: Wolfgang Fahl <wf@bitplan.com>
Maintainer-email: Wolfgang Fahl <wf@bitplan.com>
License-Expression: Apache-2.0
License-File: LICENSE
Keywords: DjVu,genealogy,nicegui,viewer
Classifier: Development Status :: 4 - Beta
Classifier: Environment :: Web Environment
Classifier: Intended Audience :: Developers
Classifier: Intended Audience :: Education
Classifier: Intended Audience :: Science/Research
Classifier: License :: OSI Approved :: Apache Software License
Classifier: Operating System :: OS Independent
Classifier: Programming Language :: Python :: 3 :: Only
Classifier: Programming Language :: Python :: 3.10
Classifier: Programming Language :: Python :: 3.11
Classifier: Programming Language :: Python :: 3.12
Classifier: Programming Language :: Python :: 3.13
Classifier: Topic :: Software Development :: Libraries :: Python Modules
Requires-Python: >=3.10
Requires-Dist: djvulibre-python>=0.9.3
Requires-Dist: ngwidgets>=0.30.3
Requires-Dist: pillow>=12.1.0
Requires-Dist: py-3rdparty-mediawiki>=0.18.1
Requires-Dist: pybasemkit>=0.2.0
Requires-Dist: pylodstorage>=0.18.6
Requires-Dist: rdflib-endpoint>=0.5.4
Requires-Dist: tqdm>=4.66.5
Provides-Extra: test
Requires-Dist: green; extra == 'test'
